LICENSE
MANIFEST.in
README.md
setup.py
apimaticcalculatordemov8/__init__.py
apimaticcalculatordemov8/api_helper.py
apimaticcalculatordemov8/apimaticcalculatordemov_8_client.py
apimaticcalculatordemov8/configuration.py
apimaticcalculatordemov8/decorators.py
apimaticcalculatordemov8.egg-info/PKG-INFO
apimaticcalculatordemov8.egg-info/SOURCES.txt
apimaticcalculatordemov8.egg-info/dependency_links.txt
apimaticcalculatordemov8.egg-info/requires.txt
apimaticcalculatordemov8.egg-info/top_level.txt
apimaticcalculatordemov8/controllers/__init__.py
apimaticcalculatordemov8/controllers/base_controller.py
apimaticcalculatordemov8/controllers/oracle_paa_s_calculator_controller.py
apimaticcalculatordemov8/exceptions/__init__.py
apimaticcalculatordemov8/exceptions/api_exception.py
apimaticcalculatordemov8/http/__init__.py
apimaticcalculatordemov8/http/http_call_back.py
apimaticcalculatordemov8/http/http_client.py
apimaticcalculatordemov8/http/http_context.py
apimaticcalculatordemov8/http/http_method_enum.py
apimaticcalculatordemov8/http/http_request.py
apimaticcalculatordemov8/http/http_response.py
apimaticcalculatordemov8/http/requests_client.py
apimaticcalculatordemov8/models/__init__.py
apimaticcalculatordemov8/models/operation_type_enum.py
tests/__init__.py
tests/http_response_catcher.py
tests/test_helper.py
tests/controllers/__init__.py
tests/controllers/controller_test_base.py
tests/controllers/test_oracle_paa_s_calculator_controller.py