Metadata-Version: 1.0
Name: apimaticcalculatordemov8
Version: 1.0.0
Summary: Simple calculator API hosted on APIMATIC
Home-page: https://apimatic.io
Author: APIMatic SDK Generator
Author-email: support@apimatic.io
License: UNKNOWN
Platform: UNKNOWN
